{
  "images": [
    {
      "type": "1 Bedroom",
      "price": "£118/Night",
      "location": "Shibuya",
      "maxResident": 2,
      "beds": 2,
      "bathroom": 1,
      "deleted_at": null,
      "is_deleted": false,
      "villa": null,
      "coliving": null,
      "created_at": "2019-10-07 13:33:07.916020+00:00",
      "description": null,
      "updated_at": "2020-10-26 13:51:36.922242+00:00",
      "filename": "Avant-Garde Serviced Apartments Shoreditch",
      "image_url": "http://lh3.googleusercontent.com/wO7Inuv6TCL-61ujLjXSVVPPVe6JjWSXfPD4o54zup3SmVCrIxD0rW0Kt9f1zGPozB6pdXr2Xg86CBjtpMy7fv_s_BDKa--tKK-20szZ9eeoYto",
      "file": 900817707,
      "backup_image_of": null,
      "guest_service": null,
      "property": 59127712,
      "order": 12,
      "page": null
    },
    {
      "type": "2 Bedroom",
      "price": "£118/Night",
      "location": "Shibuya",
      "maxResident": 4,
      "beds": 2,
      "bathroom": 2,
      "deleted_at": null,
      "is_deleted": false,
      "villa": null,
      "coliving": null,
      "created_at": "2019-10-07 13:33:04.333940+00:00",
      "description": null,
      "updated_at": "2020-10-26 13:51:36.922389+00:00",
      "filename": "Avant-Garde Serviced Apartments Shoreditch",
      "image_url": "http://lh3.googleusercontent.com/bZdyimllQve3kHALFB28YnBjr23B8oyymV6KhLDSez1tikZ6vIAxfGyOZ0vWZBGK1WX1lAN4u7j6ed5KM-E6C9DF3MYa-FEJOUeoLMrX2UQiSj4o",
      "file": 914487707,
      "backup_image_of": null,
      "guest_service": null,
      "property": 59127712,
      "order": 14,
      "page": null
    },
    {
      "type": "3 Bedroom",
      "price": "£118/Night",
      "location": "Shibuya",
      "maxResident": 6,
      "beds": 3,
      "bathroom": 2,
      "deleted_at": null,
      "is_deleted": false,
      "villa": null,
      "coliving": null,
      "created_at": "2019-10-07 13:33:02.639912+00:00",
      "description": null,
      "updated_at": "2020-10-26 13:51:36.922543+00:00",
      "filename": "Avant-Garde Serviced Apartments Shoreditch",
      "image_url": "http://lh3.googleusercontent.com/krFmd8EmvuVR-pS_wOB4kmsHmvSmbpfHOh1_FaFd2BsktopPdmn0uTwj2-3UZ-F7YLyRwC369ftw4PxvMQ728JLnDcZPIZg7T1PbO-7jSBZZplE",
      "file": 897117708,
      "backup_image_of": null,
      "guest_service": null,
      "property": 59127712,
      "order": 16,
      "page": null
    },
    {
      "type": "Studio",
      "price": "£118/Night",
      "location": "Shibuya",
      "maxResident": 1,
      "beds": 1,
      "bathroom": 1,
      "deleted_at": null,
      "is_deleted": false,
      "villa": null,
      "coliving": null,
      "created_at": "2020-08-25 13:52:07.749847+00:00",
      "description": null,
      "updated_at": "2020-10-26 13:51:36.922691+00:00",
      "filename": "Avant-Garde Serviced Apartments Shoreditch",
      "image_url": "http://lh3.googleusercontent.com/gFSrNE-fuJ10sfZWaS-cUajVTx5lR4mTR7OLJkN12ganCywKJdSOKwY8iCXzAthXwYWqRVOGtXylMNuIlS5nAvr9xTSBNQn5_NxSwD3MemIXt3KE",
      "file": 1019917708,
      "backup_image_of": null,
      "guest_service": null,
      "property": 59127712,
      "order": 18,
      "page": null
    }
  ]
}
